CHANGES.txt
DEPENDENCES.txt
README.txt
setup.py
src/ng/__init__.py
src/ng.skin.eaglenest.egg-info/PKG-INFO
src/ng.skin.eaglenest.egg-info/SOURCES.txt
src/ng.skin.eaglenest.egg-info/dependency_links.txt
src/ng.skin.eaglenest.egg-info/namespace_packages.txt
src/ng.skin.eaglenest.egg-info/not-zip-safe
src/ng.skin.eaglenest.egg-info/requires.txt
src/ng.skin.eaglenest.egg-info/top_level.txt
src/ng/skin/__init__.py
src/ng/skin/eaglenest/__init__.py
src/ng/skin/eaglenest/configure.zcml
src/ng/skin/eaglenest/interfaces.py
src/ng/skin/eaglenest/ng.skin.eaglenest.txt
src/ng/skin/eaglenest/remark.txt
src/ng/skin/eaglenest/skeleton.pt
src/ng/skin/eaglenest/style.css
src/ng/skin/eaglenest/style_ie.css
src/ng/skin/eaglenest/article/__init__.py
src/ng/skin/eaglenest/article/article.pt
src/ng/skin/eaglenest/article/article.py
src/ng/skin/eaglenest/article/configure.zcml
src/ng/skin/eaglenest/etc/ng.skin.eaglenest-configure.zcml
src/ng/skin/eaglenest/images/bottomlogo.png
src/ng/skin/eaglenest/images/logo.gif
src/ng/skin/eaglenest/images/toplogo.png
src/ng/skin/eaglenest/main/__init__.py
src/ng/skin/eaglenest/main/configure.zcml
src/ng/skin/eaglenest/main/main.css
src/ng/skin/eaglenest/main/main.pt